CHANGES.rst
LICENSE.txt
MANIFEST.in
README.rst
pydgutils_bootstrap.py
setup.cfg
setup.py
./src/rabird/__init__.py
./src/rabird.core.egg-info/PKG-INFO
./src/rabird.core.egg-info/SOURCES.txt
./src/rabird.core.egg-info/dependency_links.txt
./src/rabird.core.egg-info/namespace_packages.txt
./src/rabird.core.egg-info/not-zip-safe
./src/rabird.core.egg-info/requires.txt
./src/rabird.core.egg-info/top_level.txt
./src/rabird/core/__init__.py
./src/rabird/core/configparser.py
./src/rabird/core/cstring.py
./src/rabird/core/datetime.py
./src/rabird/core/decorators.py
./src/rabird/core/exceptions.py
./src/rabird/core/html.py
./src/rabird/core/logging.py
./src/rabird/core/system.py
./src/rabird/core/windows_api.py
./src/rabird/core/windows_fix.py
./src/rabird/core/distutils/__init__.py
./src/rabird/core/distutils/downloader.py
src/__init__.py
src/rabird/__init__.py
src/rabird.core.egg-info/PKG-INFO
src/rabird.core.egg-info/SOURCES.txt
src/rabird.core.egg-info/dependency_links.txt
src/rabird.core.egg-info/namespace_packages.txt
src/rabird.core.egg-info/not-zip-safe
src/rabird.core.egg-info/requires.txt
src/rabird.core.egg-info/top_level.txt
src/rabird/core/__init__.py
src/rabird/core/configparser.py
src/rabird/core/cstring.py
src/rabird/core/datetime.py
src/rabird/core/decorators.py
src/rabird/core/exceptions.py
src/rabird/core/html.py
src/rabird/core/logging.py
src/rabird/core/system.py
src/rabird/core/windows_api.py
src/rabird/core/windows_fix.py
src/rabird/core/distutils/__init__.py
src/rabird/core/distutils/downloader.py