Metadata-Version: 1.1
Name: rabird.core
Version: 0.3.14
Summary: A library contained miscellaneous functions and fixes that used during our development
Home-page: https://github.com/starofrainnight/rabird.core
Author: Hong-She Liang
Author-email: starofrainnight@gmail.com
License: UNKNOWN
Platform: UNKNOWN
Classifier: Development Status :: 3 - Alpha
Classifier: Intended Audience :: Developers
Classifier: License :: OSI Approved :: MIT License
Classifier: Operating System :: OS Independent
Classifier: Programming Language :: Python :: 2
Classifier: Programming Language :: Python :: 3
Classifier: Programming Language :: Python :: Implementation :: CPython
Classifier: Topic :: Software Development :: Libraries
